{
  "content" :[

    {
    "superHeading": "Medium Duty Castors",
    "heading": "RG Series",
    "code":"rg",
    "subHeading": "Excellent durability. Ideal for rugged factory spaces.",
    "image": "product-images/best-sellers-temp.png",
    "loadCapacity":{
      "tag": "load capacity",
      "quantity": "Upto 120 kgs"
      } ,
    "wheelDiameter": {
      "tag" :"wheel diameter",
      "quantity": "80 - 100 mm"
      },
    "redirectUrl": "/",
    "meta":{
      "configurable": true,
      "groupType": "series"
    }
  },
  {
    "superHeading": "Medium Duty Castors",
    "heading": "DXM Series",
    "code":"dxm",
    "subHeading": "Excellent durability. Ideal for rugged factory spaces.",
    "image": "product-images/best-sellers-temp.png",
    "loadCapacity":{
      "tag": "load capacity",
      "quantity": "Upto 120 kgs"
      } ,
    "wheelDiameter": null,
    "redirectUrl": "/",
    "meta":{
      "configurable": false,
      "groupType": "series"
    }
  },
  {
    "superHeading": "Heavy Duty Castors",
    "heading": "MRN Series",
    "code": "mrn",
    "subHeading": "Compact with a high load factor. Cost friendly castors",
    "image": "product-images/best-sellers-temp.png",
    "loadCapacity":{
      "tag": "load capacity",
      "quantity": "Upto 120 kgs"
      } ,
    "wheelDiameter": {
      "tag" :"wheel diameter",
      "quantity": "80 - 100 mm"
      },
    "redirectUrl": "/heavy-duty-castors#mrn-anchor",
    "meta":{
      "configurable": true,
      "groupType": "series"
    }
  }
]
}
